{
  "schema_version": 1,
  "canonical_cases": [
    {"name":"query_address_project","type":"QueryAddress","value":"ldl:project:p:query:q"},
    {"name":"query_address_pack","type":"QueryAddress","value":"ldl:pack:publisher:pack:query:q"},
    {"name":"parameter_address_project","type":"ParameterAddress","value":"ldl:project:p:query:q:parameter:x"},
    {"name":"parameter_address_pack","type":"ParameterAddress","value":"ldl:pack:publisher:pack:query:q:parameter:x"},
    {"name":"select_all_typed_sets","type":"QueryRecipeSelect","value":{"entity_type_addresses":["ldl:project:p:entity-type:a","ldl:project:p:entity-type:b"],"layer_addresses":["ldl:project:p:layer:a","ldl:project:p:layer:b"],"relation_type_addresses":["ldl:project:p:relation-type:a","ldl:project:p:relation-type:b"],"root_addresses":["ldl:project:p:entity:a","ldl:project:p:entity:b"]}},
    {"name":"traversal_zero_range","type":"QueryRecipeTraversal","value":{"direction":"outgoing","min_depth":"0","max_depth":"0","cycle_policy":"error"}},
    {"name":"traversal_safe_integer_boundary","type":"QueryRecipeTraversal","value":{"direction":"both","min_depth":"9007199254740991","max_depth":"9007199254740991","cycle_policy":"include_cycle_ref","relation_type_addresses":[]}},
    {"name":"dependencies_all_typed_sets","type":"QueryRecipeDependencies","value":{"column_addresses":["ldl:project:p:entity-type:t:column:c"],"entity_addresses":["ldl:project:p:entity:e"],"entity_type_addresses":["ldl:project:p:entity-type:t"],"layer_addresses":["ldl:project:p:layer:l"],"parameter_addresses":["ldl:project:p:query:q:parameter:x"],"relation_addresses":["ldl:project:p:relation:r"],"relation_type_addresses":["ldl:project:p:relation-type:t"],"state_reads":[]}},
    {"name":"predicate_address_set","type":"RecipePredicateValue","value":{"kind":"address_set","address_values":["ldl:project:p:entity:a","ldl:project:p:entity:b"]}},
    {"name":"predicate_parameter","type":"RecipePredicateValue","value":{"kind":"parameter","parameter_address":"ldl:project:p:query:q:parameter:x"}},
    {"name":"predicate_type_set","type":"RecipePredicate","value":{"kind":"rows","quantifier":"any","type_addresses":["ldl:project:p:entity-type:t"],"predicate":{"kind":"all","children":[]}}},
    {"name":"row_column_set","type":"RecipeRowPredicate","value":{"kind":"cell","column_addresses":["ldl:project:p:entity-type:t:column:a"],"operand_type":{"kind":"scalar","scalar_type":"string"},"operator":"exists"}},
    {"name":"parameter_enum_contract","type":"QueryRecipeParameter","value":{"id":"x","address":"ldl:project:p:query:q:parameter:x","value_type":"enum","enum_values":["active","preferred"],"reserved_enum_values":["legacy","retired"],"required":false}},
    {"name":"parameter_range_contract","type":"QueryRecipeParameter","value":{"id":"x","address":"ldl:project:p:query:q:parameter:x","value_type":"number","reserved_enum_values":[],"required":false,"min":"-1","max":"1","default":{"kind":"number","number_value":"0.5"}}},
    {"name":"parameter_unicode_scalar_reservations","type":"QueryRecipeParameter","value":{"id":"x","address":"ldl:project:p:query:q:parameter:x","value_type":"enum","enum_values":["active"],"reserved_enum_values":["a","ࢗ","😀"],"required":false}},
    {"name":"query_recipe_minimal","type":"QueryRecipe","value":{"address":"ldl:project:p:query:all","annotations":{},"dependencies":{"column_addresses":[],"entity_addresses":[],"entity_type_addresses":[],"layer_addresses":[],"parameter_addresses":[],"relation_addresses":[],"relation_type_addresses":[],"state_reads":[]},"display_name":"All","id":"all","parameters":[],"relation_where":{"children":[],"kind":"all"},"reserved_parameter_ids":[],"result":[],"select":{},"state_input":"none","tags":[],"where":{"children":[],"kind":"all"}}},
    {"name":"query_recipe_complete_sets","type":"QueryRecipe","value":{"address":"ldl:project:p:query:q","annotations":{},"dependencies":{"column_addresses":[],"entity_addresses":[],"entity_type_addresses":[],"layer_addresses":[],"parameter_addresses":["ldl:project:p:query:q:parameter:x"],"relation_addresses":[],"relation_type_addresses":[],"state_reads":[]},"display_name":"Q","id":"q","parameters":[{"id":"x","address":"ldl:project:p:query:q:parameter:x","value_type":"string","reserved_enum_values":[],"required":false}],"relation_where":{"kind":"all","children":[]},"reserved_parameter_ids":["old"],"result":["seed_entities","traversed_entities","path_relations","induced_relations"],"select":{},"state_input":"none","tags":["alpha","😀"],"traverse":{"direction":"outgoing","min_depth":"0","max_depth":"2","cycle_policy":"visit_once"},"where":{"kind":"field","field":"id","operand_type":{"kind":"scalar","scalar_type":"string"},"operator":"eq","value":{"kind":"parameter","parameter_address":"ldl:project:p:query:q:parameter:x"}}}},
    {"name":"query_recipe_pack_owned_parameter","type":"QueryRecipe","value":{"address":"ldl:pack:publisher:pack:query:q","annotations":{},"dependencies":{"column_addresses":[],"entity_addresses":[],"entity_type_addresses":[],"layer_addresses":[],"parameter_addresses":[],"relation_addresses":[],"relation_type_addresses":[],"state_reads":[]},"display_name":"Q","id":"q","parameters":[{"id":"x","address":"ldl:pack:publisher:pack:query:q:parameter:x","value_type":"string","reserved_enum_values":[],"required":false}],"relation_where":{"kind":"all","children":[]},"reserved_parameter_ids":[],"result":[],"select":{},"state_input":"none","tags":[],"where":{"kind":"all","children":[]}}},
    {"name":"result_schema_order","type":"QueryRecipe","value":{"address":"ldl:project:p:query:q","annotations":{},"dependencies":{"column_addresses":[],"entity_addresses":[],"entity_type_addresses":[],"layer_addresses":[],"parameter_addresses":[],"relation_addresses":[],"relation_type_addresses":[],"state_reads":[]},"display_name":"Q","id":"q","parameters":[],"relation_where":{"kind":"all","children":[]},"reserved_parameter_ids":[],"result":["seed_entities","path_relations","induced_relations"],"select":{},"state_input":"none","tags":[],"where":{"kind":"all","children":[]}}},
    {"name":"empty_dependencies","type":"QueryRecipeDependencies","value":{"column_addresses":[],"entity_addresses":[],"entity_type_addresses":[],"layer_addresses":[],"parameter_addresses":[],"relation_addresses":[],"relation_type_addresses":[],"state_reads":[]}}
  ],
  "rejection_cases": [
    {"name":"query_address_wrong_kind","type":"QueryAddress","value":"ldl:project:p:view:q"},
    {"name":"query_recipe_wrong_address_kind","type":"QueryRecipe","value":{"address":"ldl:project:p","annotations":{},"dependencies":{"column_addresses":[],"entity_addresses":[],"entity_type_addresses":[],"layer_addresses":[],"parameter_addresses":[],"relation_addresses":[],"relation_type_addresses":[],"state_reads":[]},"display_name":"Q","id":"q","parameters":[],"relation_where":{"kind":"all","children":[]},"reserved_parameter_ids":[],"result":[],"select":{},"state_input":"none","tags":[],"where":{"kind":"all","children":[]}}},
    {"name":"query_recipe_id_tail_mismatch","type":"QueryRecipe","value":{"address":"ldl:project:p:query:q","annotations":{},"dependencies":{"column_addresses":[],"entity_addresses":[],"entity_type_addresses":[],"layer_addresses":[],"parameter_addresses":[],"relation_addresses":[],"relation_type_addresses":[],"state_reads":[]},"display_name":"Q","id":"other","parameters":[],"relation_where":{"kind":"all","children":[]},"reserved_parameter_ids":[],"result":[],"select":{},"state_input":"none","tags":[],"where":{"kind":"all","children":[]}}},
    {"name":"query_recipe_invalid_local_id","type":"QueryRecipe","value":{"address":"ldl:project:p:query:q","annotations":{},"dependencies":{"column_addresses":[],"entity_addresses":[],"entity_type_addresses":[],"layer_addresses":[],"parameter_addresses":[],"relation_addresses":[],"relation_type_addresses":[],"state_reads":[]},"display_name":"Q","id":"Bad","parameters":[],"relation_where":{"kind":"all","children":[]},"reserved_parameter_ids":[],"result":[],"select":{},"state_input":"none","tags":[],"where":{"kind":"all","children":[]}}},
    {"name":"parameter_address_wrong_kind","type":"ParameterAddress","value":"ldl:project:p:view:q:export:x"},
    {"name":"parameter_id_tail_mismatch","type":"QueryRecipeParameter","value":{"id":"other","address":"ldl:project:p:query:q:parameter:x","value_type":"string","reserved_enum_values":[],"required":false}},
    {"name":"parameter_invalid_local_id","type":"QueryRecipeParameter","value":{"id":"Bad","address":"ldl:project:p:query:q:parameter:x","value_type":"string","reserved_enum_values":[],"required":false}},
    {"name":"query_parameter_wrong_owner","type":"QueryRecipe","value":{"address":"ldl:project:p:query:q","annotations":{},"dependencies":{"column_addresses":[],"entity_addresses":[],"entity_type_addresses":[],"layer_addresses":[],"parameter_addresses":[],"relation_addresses":[],"relation_type_addresses":[],"state_reads":[]},"display_name":"Q","id":"q","parameters":[{"id":"x","address":"ldl:project:p:query:other:parameter:x","value_type":"string","reserved_enum_values":[],"required":false}],"relation_where":{"kind":"all","children":[]},"reserved_parameter_ids":[],"result":[],"select":{},"state_input":"none","tags":[],"where":{"kind":"all","children":[]}}},
    {"name":"query_duplicate_parameter_identity","type":"QueryRecipe","value":{"address":"ldl:project:p:query:q","annotations":{},"dependencies":{"column_addresses":[],"entity_addresses":[],"entity_type_addresses":[],"layer_addresses":[],"parameter_addresses":[],"relation_addresses":[],"relation_type_addresses":[],"state_reads":[]},"display_name":"Q","id":"q","parameters":[{"id":"x","address":"ldl:project:p:query:q:parameter:x","value_type":"string","reserved_enum_values":[],"required":false},{"id":"x","address":"ldl:project:p:query:q:parameter:x","value_type":"string","reserved_enum_values":[],"required":false}],"relation_where":{"kind":"all","children":[]},"reserved_parameter_ids":[],"result":[],"select":{},"state_input":"none","tags":[],"where":{"kind":"all","children":[]}}},
    {"name":"query_active_reserved_parameter_overlap","type":"QueryRecipe","value":{"address":"ldl:project:p:query:q","annotations":{},"dependencies":{"column_addresses":[],"entity_addresses":[],"entity_type_addresses":[],"layer_addresses":[],"parameter_addresses":[],"relation_addresses":[],"relation_type_addresses":[],"state_reads":[]},"display_name":"Q","id":"q","parameters":[{"id":"x","address":"ldl:project:p:query:q:parameter:x","value_type":"string","reserved_enum_values":[],"required":false}],"relation_where":{"kind":"all","children":[]},"reserved_parameter_ids":["x"],"result":[],"select":{},"state_input":"none","tags":[],"where":{"kind":"all","children":[]}}},
    {"name":"reserved_parameter_duplicate","type":"QueryRecipe","value":{"address":"ldl:project:p:query:q","annotations":{},"dependencies":{"column_addresses":[],"entity_addresses":[],"entity_type_addresses":[],"layer_addresses":[],"parameter_addresses":[],"relation_addresses":[],"relation_type_addresses":[],"state_reads":[]},"display_name":"Q","id":"q","parameters":[],"relation_where":{"kind":"all","children":[]},"reserved_parameter_ids":["old","old"],"result":[],"select":{},"state_input":"none","tags":[],"where":{"kind":"all","children":[]}}},
    {"name":"reserved_parameter_reverse","type":"QueryRecipe","value":{"address":"ldl:project:p:query:q","annotations":{},"dependencies":{"column_addresses":[],"entity_addresses":[],"entity_type_addresses":[],"layer_addresses":[],"parameter_addresses":[],"relation_addresses":[],"relation_type_addresses":[],"state_reads":[]},"display_name":"Q","id":"q","parameters":[],"relation_where":{"kind":"all","children":[]},"reserved_parameter_ids":["z","a"],"result":[],"select":{},"state_input":"none","tags":[],"where":{"kind":"all","children":[]}}},
    {"name":"reserved_parameter_invalid_grammar","type":"QueryRecipe","value":{"address":"ldl:project:p:query:q","annotations":{},"dependencies":{"column_addresses":[],"entity_addresses":[],"entity_type_addresses":[],"layer_addresses":[],"parameter_addresses":[],"relation_addresses":[],"relation_type_addresses":[],"state_reads":[]},"display_name":"Q","id":"q","parameters":[],"relation_where":{"kind":"all","children":[]},"reserved_parameter_ids":["bad-id"],"result":[],"select":{},"state_input":"none","tags":[],"where":{"kind":"all","children":[]}}},
    {"name":"query_tags_duplicate","type":"QueryRecipe","value":{"address":"ldl:project:p:query:q","annotations":{},"dependencies":{"column_addresses":[],"entity_addresses":[],"entity_type_addresses":[],"layer_addresses":[],"parameter_addresses":[],"relation_addresses":[],"relation_type_addresses":[],"state_reads":[]},"display_name":"Q","id":"q","parameters":[],"relation_where":{"kind":"all","children":[]},"reserved_parameter_ids":[],"result":[],"select":{},"state_input":"none","tags":["a","a"],"where":{"kind":"all","children":[]}}},
    {"name":"query_tags_reverse","type":"QueryRecipe","value":{"address":"ldl:project:p:query:q","annotations":{},"dependencies":{"column_addresses":[],"entity_addresses":[],"entity_type_addresses":[],"layer_addresses":[],"parameter_addresses":[],"relation_addresses":[],"relation_type_addresses":[],"state_reads":[]},"display_name":"Q","id":"q","parameters":[],"relation_where":{"kind":"all","children":[]},"reserved_parameter_ids":[],"result":[],"select":{},"state_input":"none","tags":["😀","a"],"where":{"kind":"all","children":[]}}},
    {"name":"result_duplicate","type":"QueryRecipe","value":{"address":"ldl:project:p:query:q","annotations":{},"dependencies":{"column_addresses":[],"entity_addresses":[],"entity_type_addresses":[],"layer_addresses":[],"parameter_addresses":[],"relation_addresses":[],"relation_type_addresses":[],"state_reads":[]},"display_name":"Q","id":"q","parameters":[],"relation_where":{"kind":"all","children":[]},"reserved_parameter_ids":[],"result":["seed_entities","seed_entities"],"select":{},"state_input":"none","tags":[],"where":{"kind":"all","children":[]}}},
    {"name":"result_reverse","type":"QueryRecipe","value":{"address":"ldl:project:p:query:q","annotations":{},"dependencies":{"column_addresses":[],"entity_addresses":[],"entity_type_addresses":[],"layer_addresses":[],"parameter_addresses":[],"relation_addresses":[],"relation_type_addresses":[],"state_reads":[]},"display_name":"Q","id":"q","parameters":[],"relation_where":{"kind":"all","children":[]},"reserved_parameter_ids":[],"result":["induced_relations","seed_entities"],"select":{},"state_input":"none","tags":[],"where":{"kind":"all","children":[]}}},
    {"name":"result_noncanonical_schema_order","type":"QueryRecipe","value":{"address":"ldl:project:p:query:q","annotations":{},"dependencies":{"column_addresses":[],"entity_addresses":[],"entity_type_addresses":[],"layer_addresses":[],"parameter_addresses":[],"relation_addresses":[],"relation_type_addresses":[],"state_reads":[]},"display_name":"Q","id":"q","parameters":[],"relation_where":{"kind":"all","children":[]},"reserved_parameter_ids":[],"result":["seed_entities","path_relations","traversed_entities"],"select":{},"state_input":"none","tags":[],"where":{"kind":"all","children":[]}}},
    {"name":"select_layer_wrong_kind","type":"QueryRecipeSelect","value":{"layer_addresses":["ldl:project:p:entity:e"]}},
    {"name":"select_entity_type_wrong_kind","type":"QueryRecipeSelect","value":{"entity_type_addresses":["ldl:project:p:relation-type:t"]}},
    {"name":"select_relation_type_wrong_kind","type":"QueryRecipeSelect","value":{"relation_type_addresses":["ldl:project:p:entity-type:t"]}},
    {"name":"select_root_wrong_kind","type":"QueryRecipeSelect","value":{"root_addresses":["ldl:project:p:query:q"]}},
    {"name":"select_duplicate","type":"QueryRecipeSelect","value":{"entity_type_addresses":["ldl:project:p:entity-type:t","ldl:project:p:entity-type:t"]}},
    {"name":"select_reverse","type":"QueryRecipeSelect","value":{"root_addresses":["ldl:project:p:entity:b","ldl:project:p:entity:a"]}},
    {"name":"traversal_relation_type_wrong_kind","type":"QueryRecipeTraversal","value":{"direction":"outgoing","min_depth":"0","max_depth":"1","cycle_policy":"error","relation_type_addresses":["ldl:project:p:entity-type:t"]}},
    {"name":"traversal_relation_type_duplicate","type":"QueryRecipeTraversal","value":{"direction":"outgoing","min_depth":"0","max_depth":"1","cycle_policy":"error","relation_type_addresses":["ldl:project:p:relation-type:t","ldl:project:p:relation-type:t"]}},
    {"name":"traversal_relation_type_reverse","type":"QueryRecipeTraversal","value":{"direction":"outgoing","min_depth":"0","max_depth":"1","cycle_policy":"error","relation_type_addresses":["ldl:project:p:relation-type:z","ldl:project:p:relation-type:a"]}},
    {"name":"traversal_depth_leading_zero","type":"QueryRecipeTraversal","value":{"direction":"outgoing","min_depth":"00","max_depth":"1","cycle_policy":"error"}},
    {"name":"traversal_depth_negative","type":"QueryRecipeTraversal","value":{"direction":"outgoing","min_depth":"-1","max_depth":"1","cycle_policy":"error"}},
    {"name":"traversal_depth_overflow","type":"QueryRecipeTraversal","value":{"direction":"outgoing","min_depth":"0","max_depth":"9007199254740992","cycle_policy":"error"}},
    {"name":"traversal_depth_inversion","type":"QueryRecipeTraversal","value":{"direction":"outgoing","min_depth":"10","max_depth":"9","cycle_policy":"error"}},
    {"name":"dependency_column_wrong_kind","type":"QueryRecipeDependencies","value":{"column_addresses":["ldl:project:p:entity-type:t"],"entity_addresses":[],"entity_type_addresses":[],"layer_addresses":[],"parameter_addresses":[],"relation_addresses":[],"relation_type_addresses":[],"state_reads":[]}},
    {"name":"dependency_entity_wrong_kind","type":"QueryRecipeDependencies","value":{"column_addresses":[],"entity_addresses":["ldl:project:p:relation:r"],"entity_type_addresses":[],"layer_addresses":[],"parameter_addresses":[],"relation_addresses":[],"relation_type_addresses":[],"state_reads":[]}},
    {"name":"dependency_entity_type_wrong_kind","type":"QueryRecipeDependencies","value":{"column_addresses":[],"entity_addresses":[],"entity_type_addresses":["ldl:project:p:relation-type:t"],"layer_addresses":[],"parameter_addresses":[],"relation_addresses":[],"relation_type_addresses":[],"state_reads":[]}},
    {"name":"dependency_layer_wrong_kind","type":"QueryRecipeDependencies","value":{"column_addresses":[],"entity_addresses":[],"entity_type_addresses":[],"layer_addresses":["ldl:project:p:entity:e"],"parameter_addresses":[],"relation_addresses":[],"relation_type_addresses":[],"state_reads":[]}},
    {"name":"dependency_parameter_wrong_kind","type":"QueryRecipeDependencies","value":{"column_addresses":[],"entity_addresses":[],"entity_type_addresses":[],"layer_addresses":[],"parameter_addresses":["ldl:project:p:query:q"],"relation_addresses":[],"relation_type_addresses":[],"state_reads":[]}},
    {"name":"dependency_relation_wrong_kind","type":"QueryRecipeDependencies","value":{"column_addresses":[],"entity_addresses":[],"entity_type_addresses":[],"layer_addresses":[],"parameter_addresses":[],"relation_addresses":["ldl:project:p:entity:e"],"relation_type_addresses":[],"state_reads":[]}},
    {"name":"dependency_relation_type_wrong_kind","type":"QueryRecipeDependencies","value":{"column_addresses":[],"entity_addresses":[],"entity_type_addresses":[],"layer_addresses":[],"parameter_addresses":[],"relation_addresses":[],"relation_type_addresses":["ldl:project:p:entity-type:t"],"state_reads":[]}},
    {"name":"dependency_duplicate","type":"QueryRecipeDependencies","value":{"column_addresses":[],"entity_addresses":["ldl:project:p:entity:e","ldl:project:p:entity:e"],"entity_type_addresses":[],"layer_addresses":[],"parameter_addresses":[],"relation_addresses":[],"relation_type_addresses":[],"state_reads":[]}},
    {"name":"dependency_reverse","type":"QueryRecipeDependencies","value":{"column_addresses":["ldl:project:p:entity-type:t:column:z","ldl:project:p:entity-type:t:column:a"],"entity_addresses":[],"entity_type_addresses":[],"layer_addresses":[],"parameter_addresses":[],"relation_addresses":[],"relation_type_addresses":[],"state_reads":[]}},
    {"name":"predicate_address_set_duplicate","type":"RecipePredicateValue","value":{"kind":"address_set","address_values":["ldl:project:p:entity:e","ldl:project:p:entity:e"]}},
    {"name":"predicate_address_set_reverse","type":"RecipePredicateValue","value":{"kind":"address_set","address_values":["ldl:project:p:entity:z","ldl:project:p:entity:a"]}},
    {"name":"predicate_parameter_wrong_kind","type":"RecipePredicateValue","value":{"kind":"parameter","parameter_address":"ldl:project:p:query:q"}},
    {"name":"predicate_type_wrong_kind","type":"RecipePredicate","value":{"kind":"rows","quantifier":"any","type_addresses":["ldl:project:p:entity:e"],"predicate":{"kind":"all","children":[]}}},
    {"name":"predicate_type_duplicate","type":"RecipePredicate","value":{"kind":"rows","quantifier":"any","type_addresses":["ldl:project:p:entity-type:t","ldl:project:p:entity-type:t"],"predicate":{"kind":"all","children":[]}}},
    {"name":"predicate_type_reverse","type":"RecipePredicate","value":{"kind":"rows","quantifier":"any","type_addresses":["ldl:project:p:relation-type:t","ldl:project:p:entity-type:t"],"predicate":{"kind":"all","children":[]}}},
    {"name":"row_column_wrong_kind","type":"RecipeRowPredicate","value":{"kind":"cell","column_addresses":["ldl:project:p:entity-type:t"],"operator":"exists"}},
    {"name":"row_column_duplicate","type":"RecipeRowPredicate","value":{"kind":"cell","column_addresses":["ldl:project:p:entity-type:t:column:c","ldl:project:p:entity-type:t:column:c"],"operator":"exists"}},
    {"name":"row_column_reverse","type":"RecipeRowPredicate","value":{"kind":"cell","column_addresses":["ldl:project:p:entity-type:t:column:z","ldl:project:p:entity-type:t:column:a"],"operator":"exists"}},
    {"name":"parameter_enum_duplicate","type":"QueryRecipeParameter","value":{"id":"x","address":"ldl:project:p:query:q:parameter:x","value_type":"enum","enum_values":["a","a"],"reserved_enum_values":[],"required":false}},
    {"name":"parameter_reserved_enum_duplicate","type":"QueryRecipeParameter","value":{"id":"x","address":"ldl:project:p:query:q:parameter:x","value_type":"enum","enum_values":[],"reserved_enum_values":["old","old"],"required":false}},
    {"name":"parameter_reserved_enum_reverse","type":"QueryRecipeParameter","value":{"id":"x","address":"ldl:project:p:query:q:parameter:x","value_type":"enum","enum_values":[],"reserved_enum_values":["😀","a"],"required":false}},
    {"name":"parameter_active_reserved_enum_overlap","type":"QueryRecipeParameter","value":{"id":"x","address":"ldl:project:p:query:q:parameter:x","value_type":"enum","enum_values":["active"],"reserved_enum_values":["active"],"required":false}},
    {"name":"parameter_numeric_range_inversion","type":"QueryRecipeParameter","value":{"id":"x","address":"ldl:project:p:query:q:parameter:x","value_type":"number","reserved_enum_values":[],"required":false,"min":"2","max":"1"}},
    {"name":"parameter_length_range_inversion","type":"QueryRecipeParameter","value":{"id":"x","address":"ldl:project:p:query:q:parameter:x","value_type":"string","reserved_enum_values":[],"required":false,"min_length":"10","max_length":"9"}}
  ]
}
